kicksaw_integration_app_client/__init__.py
kicksaw_integration_app_client-1.0.9.dist-info/METADATA
kicksaw_integration_app_client-1.0.9.dist-info/WHEEL
kicksaw_integration_app_client-1.0.9.dist-info/RECORD
