Metadata-Version: 2.1
Name: kicksaw-integration-app-client
Version: 1.0.9
Summary: A customized simple-salesforce client for use with the integration app
Home-page: https://github.com/Kicksaw-Consulting/kicksaw-integration-app-client
Keywords: kicksaw,aws,s3,simple salesforce,csv
Author: Alex Drozd
Author-email: alex@kicksaw.com
Requires-Python: >=3.8,<4.0
Classifier: Programming Language :: Python :: 3
Classifier: Programming Language :: Python :: 3.8
Classifier: Programming Language :: Python :: 3.9
Classifier: Programming Language :: Python :: 3.10
Classifier: Programming Language :: Python :: 3.11
Requires-Dist: kicksaw-integration-utils (>=2.0.0,<3.0.0)
Project-URL: Repository, https://github.com/Kicksaw-Consulting/kicksaw-integration-app-client
